easyjapanese/__init__.py
easyjapanese/complete.py
easyjapanese/easy.py
easyjapanese/regular.py
EasyJappanese-0.0.2.dist-info/METADATA
EasyJappanese-0.0.2.dist-info/WHEEL
EasyJappanese-0.0.2.dist-info/top_level.txt
EasyJappanese-0.0.2.dist-info/RECORD
